kubespawner_keycloak/__init__.py
kubespawner_keycloak/_version.py
kubespawner_keycloak/exceptions.py
kubespawner_keycloak/k8sio.py
kubespawner_keycloak/keycloak.py
kubespawner_keycloak/objects.py
kubespawner_keycloak-0.1.4.dist-info/METADATA
kubespawner_keycloak-0.1.4.dist-info/WHEEL
kubespawner_keycloak-0.1.4.dist-info/licenses/LICENSE
kubespawner_keycloak-0.1.4.dist-info/RECORD
